docs/conf.py
examples/__init__.py
examples/test_tcp_data_transfer.py
examples/transport_integration_demo.py
examples/advanced/network_discover.py
examples/bootstrap/bootstrap.py
examples/chat/__init__.py
examples/chat/chat.py
examples/doc-examples/example_encryption_insecure.py
examples/doc-examples/example_encryption_noise.py
examples/doc-examples/example_encryption_secio.py
examples/doc-examples/example_multiplexer.py
examples/doc-examples/example_net_stream.py
examples/doc-examples/example_peer_discovery.py
examples/doc-examples/example_quic_transport.py
examples/doc-examples/example_running.py
examples/doc-examples/example_transport.py
examples/doc-examples/multiple_connections_example.py
examples/echo/__init__.py
examples/echo/echo.py
examples/echo/echo_quic.py
examples/identify/__init__.py
examples/identify/identify.py
examples/identify_push/__init__.py
examples/identify_push/identify_push_demo.py
examples/identify_push/identify_push_listener_dialer.py
examples/kademlia/kademlia.py
examples/mDNS/mDNS.py
examples/ping/__init__.py
examples/ping/ping.py
examples/pubsub/pubsub.py
examples/random_walk/random_walk.py
examples/websocket/test_tcp_echo.py
examples/websocket/test_websocket_transport.py
examples/websocket/websocket_demo.py
libp2p/__init__.py
libp2p/abc.py
libp2p/custom_types.py
libp2p/exceptions.py
libp2p/py.typed
libp2p/crypto/__init__.py
libp2p/crypto/authenticated_encryption.py
libp2p/crypto/ecc.py
libp2p/crypto/ed25519.py
libp2p/crypto/exceptions.py
libp2p/crypto/key_exchange.py
libp2p/crypto/keys.py
libp2p/crypto/rsa.py
libp2p/crypto/secp256k1.py
libp2p/crypto/serialization.py
libp2p/crypto/x25519.py
libp2p/crypto/pb/__init__.py
libp2p/crypto/pb/crypto_pb2.py
libp2p/crypto/pb/crypto_pb2.pyi
libp2p/discovery/__init__.py
libp2p/discovery/bootstrap/__init__.py
libp2p/discovery/bootstrap/bootstrap.py
libp2p/discovery/bootstrap/utils.py
libp2p/discovery/events/__init__.py
libp2p/discovery/events/peerDiscovery.py
libp2p/discovery/mdns/__init__.py
libp2p-0.3.0.dist-info/licenses/LICENSE-APACHE
libp2p-0.3.0.dist-info/licenses/LICENSE-MIT
libp2p-0.3.0.dist-info/METADATA
libp2p-0.3.0.dist-info/WHEEL
libp2p-0.3.0.dist-info/entry_points.txt
libp2p-0.3.0.dist-info/top_level.txt
libp2p-0.3.0.dist-info/RECORD
