Metadata-Version: 2.4
Name: libp2p
Version: 0.3.0
Summary: libp2p: The Python implementation of the libp2p networking stack
Maintainer-email: pacrob <pacrob-py-libp2p@proton.me>, Manu Sheel Gupta <manu@seeta.in>, Dave Grantham <dwg@linuxprogrammer.org>
License: MIT AND Apache-2.0
Project-URL: Homepage, https://github.com/libp2p/py-libp2p
Keywords: libp2p,p2p
Classifier: Development Status :: 4 - Beta
Classifier: Intended Audience :: Developers
Classifier: Natural Language :: English
Classifier: Programming Language :: Python :: 3
Classifier: Programming Language :: Python :: 3.10
Classifier: Programming Language :: Python :: 3.11
Classifier: Programming Language :: Python :: 3.12
Classifier: Programming Language :: Python :: 3.13
Requires-Python: <4.0,>=3.10
License-File: LICENSE-APACHE
License-File: LICENSE-MIT
Requires-Dist: aioquic>=1.2.0
Requires-Dist: base58>=1.0.3
Requires-Dist: coincurve==21.0.0
Requires-Dist: exceptiongroup>=1.2.0; python_version < "3.11"
Requires-Dist: fastecdsa==2.3.2; sys_platform != "win32"
Requires-Dist: grpcio>=1.41.0
Requires-Dist: lru-dict>=1.1.6
Requires-Dist: multiaddr>=0.0.11
Requires-Dist: mypy-protobuf>=3.0.0
Requires-Dist: noiseprotocol>=0.3.0
Requires-Dist: protobuf<5.0.0,>=4.25.0
Requires-Dist: pycryptodome>=3.9.2
Requires-Dist: pymultihash>=0.8.2
Requires-Dist: pynacl>=1.3.0
Requires-Dist: rpcudp>=3.0.0
Requires-Dist: trio-typing>=0.0.4
Requires-Dist: trio>=0.26.0
Requires-Dist: trio-websocket>=0.11.0
Requires-Dist: zeroconf<0.148.0,>=0.147.0
Provides-Extra: dev
Requires-Dist: build>=0.9.0; extra == "dev"
Requires-Dist: bump_my_version>=0.19.0; extra == "dev"
Requires-Dist: ipython; extra == "dev"
Requires-Dist: mypy>=1.15.0; extra == "dev"
Requires-Dist: pre-commit>=3.4.0; extra == "dev"
Requires-Dist: tox>=4.0.0; extra == "dev"
Requires-Dist: twine; extra == "dev"
Requires-Dist: wheel; extra == "dev"
Requires-Dist: setuptools>=42; extra == "dev"
Requires-Dist: sphinx>=6.0.0; extra == "dev"
Requires-Dist: sphinx_rtd_theme>=1.0.0; extra == "dev"
Requires-Dist: towncrier<25,>=24; extra == "dev"
Requires-Dist: p2pclient==0.2.0; extra == "dev"
Requires-Dist: pytest>=7.0.0; extra == "dev"
Requires-Dist: pytest-xdist>=2.4.0; extra == "dev"
Requires-Dist: pytest-trio>=0.5.2; extra == "dev"
Requires-Dist: pytest-timeout>=2.4.0; extra == "dev"
Requires-Dist: pytest-rerunfailures>=12.0; extra == "dev"
Requires-Dist: factory-boy<3.0.0,>=2.12.0; extra == "dev"
Requires-Dist: ruff>=0.11.10; extra == "dev"
Requires-Dist: pyrefly<0.18.0,>=0.17.1; extra == "dev"
Provides-Extra: docs
Requires-Dist: sphinx>=6.0.0; extra == "docs"
Requires-Dist: sphinx_rtd_theme>=1.0.0; extra == "docs"
Requires-Dist: towncrier<25,>=24; extra == "docs"
Requires-Dist: tomli; python_version < "3.11" and extra == "docs"
Provides-Extra: test
Requires-Dist: factory-boy<3.0.0,>=2.12.0; extra == "test"
Requires-Dist: p2pclient==0.2.0; extra == "test"
Requires-Dist: pytest>=7.0.0; extra == "test"
Requires-Dist: pytest-timeout>=2.4.0; extra == "test"
Requires-Dist: pytest-trio>=0.5.2; extra == "test"
Requires-Dist: pytest-xdist>=2.4.0; extra == "test"
Dynamic: license-file
